syqlorix/__init__.py
syqlorix/cli.py
syqlorix/core.py
syqlorix/core.pyi
syqlorix/py.typed
syqlorix/tailwind.py
syqlorix/templating.py
syqlorix/templating.pyi
syqlorix-1.3.2.dist-info/licenses/LICENSE
syqlorix-1.3.2.dist-info/METADATA
syqlorix-1.3.2.dist-info/WHEEL
syqlorix-1.3.2.dist-info/entry_points.txt
syqlorix-1.3.2.dist-info/top_level.txt
syqlorix-1.3.2.dist-info/RECORD
