Metadata-Version: 2.4
Name: syqlorix
Version: 1.3.2
Summary: A hyper-minimalist Python framework for building component-based web UIs and static sites with a pure Python DSL.
Author-email: "Karl Benjamin R. Bughaw" <benjo@pro.space>
License: MIT License
Project-URL: Homepage, https://github.com/Syqlorix/Syqlorix
Project-URL: Bug Tracker, https://github.com/Syqlorix/Syqlorix/issues
Keywords: html,css,javascript,dsl,web,components,state-management,static-site-generator,ui,live-reload,routing,static-server
Classifier: Development Status :: 5 - Production/Stable
Classifier: Intended Audience :: Developers
Classifier: License :: OSI Approved :: MIT License
Classifier: Programming Language :: Python :: 3
Classifier: Programming Language :: Python :: 3.8
Classifier: Programming Language :: Python :: 3.9
Classifier: Programming Language :: Python :: 3.10
Classifier: Programming Language :: Python :: 3.11
Classifier: Programming Language :: Python :: 3.12
Classifier: Topic :: Internet :: WWW/HTTP :: Dynamic Content
Classifier: Topic :: Software Development :: Libraries :: Python Modules
Classifier: Topic :: Text Processing :: Markup :: HTML
Requires-Python: >=3.8
License-File: LICENSE
Requires-Dist: click>=8.0
Requires-Dist: watchdog>=2.0
Requires-Dist: websockets>=12.0
Requires-Dist: jsmin>=3.0
Requires-Dist: cssmin>=0.2
Requires-Dist: requests>=2.25.0
Provides-Extra: tailwind
Requires-Dist: tailwind-processor; extra == "tailwind"
Provides-Extra: full
Requires-Dist: syqlorix; extra == "full"
Requires-Dist: syqlorix[tailwind]; extra == "full"
Dynamic: license-file
